flow_tts/__init__.py
flow_tts/client.py
flow_tts/py.typed
flow_tts/types.py
flow_tts/core/__init__.py
flow_tts/core/request.py
flow_tts/core/signature.py
flow_tts/data/voices-flow_01_ex.json
flow_tts/data/voices-flow_01_turbo.json
flow_tts/utils/__init__.py
flow_tts/utils/language_detector.py
flow_tts/utils/voice_resolver.py
flow_tts-0.1.0.dist-info/licenses/LICENSE
flow_tts-0.1.0.dist-info/METADATA
flow_tts-0.1.0.dist-info/WHEEL
flow_tts-0.1.0.dist-info/top_level.txt
flow_tts-0.1.0.dist-info/RECORD
