Metadata-Version: 2.4
Name: flow-tts
Version: 0.1.0
Summary: OpenAI-style TTS SDK for Tencent Cloud - Zero dependencies, Python-first
Author: Flow TTS Team
License: MIT
Project-URL: Homepage, https://github.com/chicogong/flow-tts
Project-URL: Repository, https://github.com/chicogong/flow-tts
Project-URL: Documentation, https://github.com/chicogong/flow-tts/tree/master/packages/python
Project-URL: Issues, https://github.com/chicogong/flow-tts/issues
Keywords: tts,text-to-speech,tencent-cloud,audio,synthesis,openai,flow
Classifier: Development Status :: 4 - Beta
Classifier: Intended Audience :: Developers
Classifier: License :: OSI Approved :: MIT License
Classifier: Programming Language :: Python :: 3
Classifier: Programming Language :: Python :: 3.8
Classifier: Programming Language :: Python :: 3.9
Classifier: Programming Language :: Python :: 3.10
Classifier: Programming Language :: Python :: 3.11
Classifier: Programming Language :: Python :: 3.12
Classifier: Topic :: Software Development :: Libraries :: Python Modules
Classifier: Topic :: Multimedia :: Sound/Audio :: Speech
Requires-Python: >=3.8
License-File: LICENSE
Dynamic: license-file
